browser_gpt_api/.env.template
browser_gpt_api/__init__.py
browser_gpt_api/gpt_automator.py
browser_gpt_api/server.py
browser_gpt_api/settings.py
browser_gpt_api/setup.py
browser_gpt_api/utils.py
browser_gpt_api-0.1.0.dist-info/METADATA
browser_gpt_api-0.1.0.dist-info/WHEEL
browser_gpt_api-0.1.0.dist-info/RECORD
