Metadata-Version: 2.3
Name: browser-gpt-api
Version: 0.1.0
Summary: Add your description here
Author-email: AK3847 <abdulkadir.co21d2@scet.ac.in>
Requires-Python: >=3.8
Requires-Dist: fastapi>=0.111.0
Requires-Dist: pydantic-settings>=2.3.4
Requires-Dist: pydantic>=2.7.4
Requires-Dist: requests>=2.32.3
Requires-Dist: selenium>=4.22.0
Requires-Dist: tiktoken>=0.7.0
Requires-Dist: uvicorn>=0.30.1
